focus_detection/__init__.py
focus_detection/focus_detection_image.py
focus_detection/focus_detection_video.py
focus_detection/__pycache__/__init__.cpython-37.pyc
focus_detection/__pycache__/blurryface_image.cpython-37.pyc
focus_detection/__pycache__/blurryface_video.cpython-37.pyc
focus_detection/__pycache__/focus_detection_image.cpython-37.pyc
focus_detection/__pycache__/focus_detection_video.cpython-37.pyc
focus_detection-1.0.0.dist-info/METADATA
focus_detection-1.0.0.dist-info/WHEEL
focus_detection-1.0.0.dist-info/entry_points.txt
focus_detection-1.0.0.dist-info/top_level.txt
focus_detection-1.0.0.dist-info/RECORD
