Metadata-Version: 2.1
Name: focus-detection
Version: 1.0.0
Summary: Focus Detection
Home-page: UNKNOWN
Author: Jason Darnell
Author-email: UNKNOWN
License: Proprietary
Platform: UNKNOWN
Requires-Dist: numpy
Requires-Dist: pyqt5
Requires-Dist: opencv-python
